apyt/__init__.py
apyt/analysis/__init__.py
apyt/analysis/spectrum.py
apyt/analysis/chemistry/__init__.py
apyt/analysis/chemistry/locomp.py
apyt/analysis/crystallography/__init__.py
apyt/analysis/crystallography/sdm.py
apyt/gui/__init__.py
apyt/gui/forms.py
apyt/io/__init__.py
apyt/io/config.py
apyt/io/conv.py
apyt/io/localdb.py
apyt/io/sql.py
apyt/reconstruction/__init__.py
apyt/reconstruction/basic.py
apyt/reconstruction/non_spherical.py
apyt/spectrum/__init__.py
apyt/spectrum/align.py
apyt/spectrum/fit.py
apyt_cli/reconstruction.py
apyt_cli/spectrum_align.py
apyt_cli/spectrum_fit.py
data/apyt_W_calibration_tap_01_trimmed.raw
scripts/apyt_reconstruction.py
scripts/apyt_spectrum_align.py
scripts/apyt_spectrum_fit.py
apyt-0.1.0.dev2.dist-info/METADATA
apyt-0.1.0.dev2.dist-info/WHEEL
apyt-0.1.0.dev2.dist-info/entry_points.txt
apyt-0.1.0.dev2.dist-info/licenses/LICENSE
apyt-0.1.0.dev2.dist-info/RECORD
