Metadata-Version: 2.4
Name: apyt
Version: 0.1.0.dev2
Summary: APyT is a Python package which provides modules for the evaluation of atom probe tomography (APT) data.
Project-URL: Homepage, https://apyt.mp.imw.uni-stuttgart.de/
Project-URL: Documentation, https://apyt.mp.imw.uni-stuttgart.de/
Project-URL: Changelog, https://apyt.mp.imw.uni-stuttgart.de/release.html
Project-URL: Repository, https://github.com/sebi-85/apyt
Project-URL: Issues, https://github.com/sebi-85/apyt/issues
Author-email: "Sebastian M. Eich" <Sebastian.Eich@imw.uni-stuttgart.de>
License-Expression: AGPL-3.0-or-later
License-File: LICENSE
Classifier: Development Status :: 4 - Beta
Classifier: Intended Audience :: Developers
Classifier: Intended Audience :: Science/Research
Classifier: License :: OSI Approved :: GNU Affero General Public License v3 or later (AGPLv3+)
Classifier: Operating System :: OS Independent
Classifier: Programming Language :: Python :: 3
Classifier: Topic :: Scientific/Engineering
Requires-Python: >=3.11
Requires-Dist: findiff
Requires-Dist: fujson
Requires-Dist: html2text
Requires-Dist: lmfit
Requires-Dist: matplotlib
Requires-Dist: numba>=0.57
Requires-Dist: numpy
Requires-Dist: packaging
Requires-Dist: periodictable
Requires-Dist: platformdirs
Requires-Dist: psutil
Requires-Dist: pyperclip
Requires-Dist: pyvista
Requires-Dist: pyyaml
Requires-Dist: requests
Requires-Dist: scipy>=1.11
Requires-Dist: ttkthemes
